nnAudio/Spectrogram.py
nnAudio/__init__.py
nnAudio/librosa_functions.py
nnAudio/utils.py
nnAudio/features/__init__.py
nnAudio/features/cfp.py
nnAudio/features/cqt.py
nnAudio/features/gammatone.py
nnAudio/features/griffin_lim.py
nnAudio/features/mel.py
nnAudio/features/stft.py
nnAudio/features/vqt.py
nnaudio-0.3.4.dist-info/LICENSE
nnaudio-0.3.4.dist-info/METADATA
nnaudio-0.3.4.dist-info/WHEEL
nnaudio-0.3.4.dist-info/top_level.txt
nnaudio-0.3.4.dist-info/RECORD
